mock_it_adapter/__init__.py
mock_it_adapter/client.py
mock_it_adapter/exceptions.py
mock_it_adapter/models.py
mock_it_adapter-1.0.0.dist-info/METADATA
mock_it_adapter-1.0.0.dist-info/WHEEL
mock_it_adapter-1.0.0.dist-info/licenses/LICENSE
mock_it_adapter-1.0.0.dist-info/RECORD
