Metadata-Version: 2.4
Name: mock-it-adapter
Version: 1.0.0
Summary: A Python mock_it_adapter for Mock IT API
Project-URL: Homepage, https://github.com/AlekseiSuzume/mock_it_adapter_py
Author-email: Vorobev Aleksei <aleksei.suzume@gmail.com>
License-File: LICENSE
Requires-Python: >=3.10.0
